shuttle/__init__.py
shuttle/cli/__init__.py
shuttle/cli/__main__.py
shuttle/cli/providers/__init__.py
shuttle/cli/providers/bitcoin/__init__.py
shuttle/cli/providers/bitcoin/claim.py
shuttle/cli/providers/bitcoin/decode.py
shuttle/cli/providers/bitcoin/fund.py
shuttle/cli/providers/bitcoin/htlc.py
shuttle/cli/providers/bitcoin/refund.py
shuttle/cli/providers/bitcoin/signature.py
shuttle/cli/providers/bitcoin/submit.py
shuttle/cli/providers/bytom/__init__.py
shuttle/cli/providers/bytom/claim.py
shuttle/cli/providers/bytom/decode.py
shuttle/cli/providers/bytom/fund.py
shuttle/cli/providers/bytom/htlc.py
shuttle/cli/providers/bytom/refund.py
shuttle/cli/providers/bytom/signature.py
shuttle/cli/providers/bytom/submit.py
shuttle/providers/__init__.py
shuttle/providers/config.py
shuttle/providers/bitcoin/__init__.py
shuttle/providers/bitcoin/htlc.py
shuttle/providers/bitcoin/rpc.py
shuttle/providers/bitcoin/signature.py
shuttle/providers/bitcoin/solver.py
shuttle/providers/bitcoin/transaction.py
shuttle/providers/bitcoin/utils.py
shuttle/providers/bitcoin/wallet.py
shuttle/providers/bytom/__init__.py
shuttle/providers/bytom/htlc.py
shuttle/providers/bytom/rpc.py
shuttle/providers/bytom/signature.py
shuttle/providers/bytom/solver.py
shuttle/providers/bytom/transaction.py
shuttle/providers/bytom/utils.py
shuttle/providers/bytom/wallet.py
shuttle/utils/__init__.py
shuttle/utils/exceptions.py
shuttle/utils/utils.py
pyshuttle-0.3.4.dist-info/LICENSE
pyshuttle-0.3.4.dist-info/METADATA
pyshuttle-0.3.4.dist-info/WHEEL
pyshuttle-0.3.4.dist-info/entry_points.txt
pyshuttle-0.3.4.dist-info/top_level.txt
pyshuttle-0.3.4.dist-info/RECORD
