Metadata-Version: 2.1
Name: pyshuttle
Version: 0.3.4
Summary: Cross-chain atomic swaps between the networks of two cryptocurrencies.
Home-page: https://github.com/meherett/shuttle
Author: Meheret Tesfaye
Author-email: meherett@zoho.com
License: AGPL-3.0
Keywords: cross-chain,atomic-swap,htlc,bitcoin,bytom,cryptocurrencies
Platform: UNKNOWN
Classifier: Development Status :: 5 - Production/Stable
Classifier: License :: OSI Approved :: GNU Affero General Public License v3
Classifier: Programming Language :: Python :: 3.6
Classifier: Programming Language :: Python :: 3.7
Classifier: Programming Language :: Python :: 3.8
Classifier: Topic :: Software Development
Requires-Python: >=3.6,<4
Requires-Dist: requests (<3,>=2.22.0)
Requires-Dist: cryptos (<2,>=1.36)
Requires-Dist: chainside-btcpy (<1,>=0.6.5)
Requires-Dist: mnemonic (<1,>=0.19)
Requires-Dist: py-equity (<1,>=0.1.0)
Requires-Dist: click (<8,>=7.1.2)
Requires-Dist: pybytom (<2,>=1.3.3)
Requires-Dist: six (<2,>=1.15.0)
Provides-Extra: docs
Requires-Dist: sphinx (<4,>=3.1.2) ; extra == 'docs'
Requires-Dist: sphinx-rtd-theme (<1,>=0.5.0) ; extra == 'docs'
Requires-Dist: sphinx-click (<3,>=2.5.0) ; extra == 'docs'
Provides-Extra: tests
Requires-Dist: pytest (<6,>=5.4.3) ; extra == 'tests'
Requires-Dist: pytest-cov (<3,>=2.10.0) ; extra == 'tests'
